{
  "_class": "shapePath",
  "booleanOperation": -1,
  "clippingMaskMode": 0,
  "do_objectID": "392191AF-44B1-4173-AA07-A0BBCE1D4B70",
  "edited": true,
  "exportOptions": {
    "_class": "exportOptions",
    "exportFormats": [
    ],
    "includedLayerIds": [
    ],
    "layerOptions": 0,
    "shouldTrim": false
  },
  "frame": {
    "_class": "rect",
    "constrainProportions": false,
    "height": 14.81698496202936,
    "width": 6.377667678525818,
    "x": 1.71706437498829,
    "y": 2.576539321713593
  },
  "hasClippingMask": false,
  "isClosed": true,
  "isFixedToViewport": false,
  "isFlippedHorizontal": false,
  "isFlippedVertical": false,
  "isLocked": false,
  "isVisible": true,
  "layerListExpandedType": 0,
  "maintainScrollPosition": false,
  "name": "🎨 Icon Colour",
  "nameIsFixed": false,
  "pointRadiusBehaviour": 1,
  "points": [
    {
      "_class": "curvePoint",
      "cornerRadius": 0,
      "curveFrom": "{0.048108229166836505, 0.00037868908195398644}",
      "curveMode": 4,
      "curveTo": "{0.05254856157923922, 0.0011169859721274168}",
      "hasCurveFrom": true,
      "hasCurveTo": false,
      "point": "{0.05254856157923922, 0.0011169859721274168}"
    },
    {
      "_class": "curvePoint",
      "cornerRadius": 0,
      "curveFrom": "{0.017294794168256935, 0}",
      "curveMode": 3,
      "curveTo": "{0.043389114844442779, 0}",
      "hasCurveFrom": true,
      "hasCurveTo": true,
      "point": "{0.038629003952223441, 0}"
    },
    {
      "_class": "curvePoint",
      "cornerRadius": 0,
      "curveFrom": "{0, 0.016627063507932464}",
      "curveMode": 4,
      "curveTo": "{0, 0.0074441898980332792}",
      "hasCurveFrom": false,
      "hasCurveTo": true,
      "point": "{0, 0.016627063507932464}"
    },
    {
      "_class": "curvePoint",
      "cornerRadius": 0,
      "curveFrom": "{1.3926382879601928e-16, 0.85224440614038499}",
      "curveMode": 4,
      "curveTo": "{0, 0.84516778923835811}",
      "hasCurveFrom": true,
      "hasCurveTo": false,
      "point": "{0, 0.84516778923835811}"
    },
    {
      "_class": "curvePoint",
      "cornerRadius": 0,
      "curveFrom": "{0.025933893565665257, 0.86087129577221455}",
      "curveMode": 4,
      "curveTo": "{0.010406279660446393, 0.85854562274047552}",
      "hasCurveFrom": false,
      "hasCurveTo": true,
      "point": "{0.025933893565665257, 0.86087129577221455}"
    },
    {
      "_class": "curvePoint",
      "cornerRadius": 0,
      "curveFrom": "{0.95275776052190908, 0.99968781231552584}",
      "curveMode": 4,
      "curveTo": "{0.94867588566121819, 0.99907644302592402}",
      "hasCurveFrom": true,
      "hasCurveTo": false,
      "point": "{0.94867588566121819, 0.99907644302592402}"
    },
    {
      "_class": "curvePoint",
      "cornerRadius": 0,
      "curveFrom": "{0.98270520583174326, 1}",
      "curveMode": 3,
      "curveTo": "{0.95704905735250401, 1}",
      "hasCurveFrom": true,
      "hasCurveTo": true,
      "point": "{0.96137099604777665, 1}"
    },
    {
      "_class": "curvePoint",
      "cornerRadius": 0,
      "curveFrom": "{1, 0.98337293649206781}",
      "curveMode": 4,
      "curveTo": "{1, 0.99255581010196692}",
      "hasCurveFrom": false,
      "hasCurveTo": true,
      "point": "{1, 0.98337293649206781}"
    },
    {
      "_class": "curvePoint",
      "cornerRadius": 0,
      "curveFrom": "{0.99999999999999967, 0.16318100959467155}",
      "curveMode": 4,
      "curveTo": "{1, 0.1700519605480221}",
      "hasCurveFrom": true,
      "hasCurveTo": false,
      "point": "{1, 0.1700519605480221}"
    },
    {
      "_class": "curvePoint",
      "cornerRadius": 0,
      "curveFrom": "{0.975290553674792, 0.15454188301221711}",
      "curveMode": 4,
      "curveTo": "{0.99018118860062299, 0.15701775833806944}",
      "hasCurveFrom": false,
      "hasCurveTo": true,
      "point": "{0.975290553674792, 0.15454188301221711}"
    }
  ],
  "resizingConstraint": 63,
  "resizingType": 0,
  "rotation": 0,
  "shouldBreakMaskChain": false,
  "style": {
    "_class": "style",
    "blur": {
      "_class": "blur",
      "center": "{0.5, 0.5}",
      "isEnabled": false,
      "motionAngle": 0,
      "radius": 10,
      "saturation": 1,
      "type": 0
    },
    "borderOptions": {
      "_class": "borderOptions",
      "dashPattern": [
      ],
      "isEnabled": false,
      "lineCapStyle": 2,
      "lineJoinStyle": 0
    },
    "borders": [
      {
        "_class": "border",
        "color": {
          "_class": "color",
          "alpha": 1,
          "blue": 0.592,
          "green": 0.592,
          "red": 0.592
        },
        "contextSettings": {
          "_class": "graphicsContextSettings",
          "blendMode": 0,
          "opacity": 1
        },
        "fillType": 0,
        "gradient": {
          "_class": "gradient",
          "elipseLength": 0,
          "from": "{0.5, 0}",
          "gradientType": 0,
          "stops": [
            {
              "_class": "gradientStop",
              "color": {
                "_class": "color",
                "alpha": 1,
                "blue": 1,
                "green": 1,
                "red": 1
              },
              "position": 0
            },
            {
              "_class": "gradientStop",
              "color": {
                "_class": "color",
                "alpha": 1,
                "blue": 0,
                "green": 0,
                "red": 0
              },
              "position": 1
            }
          ],
          "to": "{0.5, 1}"
        },
        "isEnabled": false,
        "position": 1,
        "thickness": 1
      }
    ],
    "colorControls": {
      "_class": "colorControls",
      "brightness": 0,
      "contrast": 1,
      "hue": 0,
      "isEnabled": true,
      "saturation": 1
    },
    "contextSettings": {
      "_class": "graphicsContextSettings",
      "blendMode": 0,
      "opacity": 1
    },
    "do_objectID": "79802E52-B64E-4CDD-B6E0-A93660F8C7BE",
    "endMarkerType": 0,
    "fills": [
      {
        "_class": "fill",
        "color": {
          "_class": "color",
          "alpha": 1,
          "blue": 0,
          "green": 0,
          "red": 0
        },
        "contextSettings": {
          "_class": "graphicsContextSettings",
          "blendMode": 0,
          "opacity": 1
        },
        "fillType": 0,
        "gradient": {
          "_class": "gradient",
          "elipseLength": 0,
          "from": "{0.5, 0}",
          "gradientType": 0,
          "stops": [
            {
              "_class": "gradientStop",
              "color": {
                "_class": "color",
                "alpha": 1,
                "blue": 1,
                "green": 1,
                "red": 1
              },
              "position": 0
            },
            {
              "_class": "gradientStop",
              "color": {
                "_class": "color",
                "alpha": 1,
                "blue": 0,
                "green": 0,
                "red": 0
              },
              "position": 1
            }
          ],
          "to": "{0.5, 1}"
        },
        "isEnabled": true,
        "noiseIndex": 0,
        "noiseIntensity": 0,
        "patternFillType": 1,
        "patternTileScale": 1
      }
    ],
    "innerShadows": [
    ],
    "miterLimit": 10,
    "shadows": [
    ],
    "startMarkerType": 0,
    "windingRule": 1
  }
}