{
  "_class": "shapePath",
  "booleanOperation": -1,
  "clippingMaskMode": 0,
  "do_objectID": "F5066FEA-7541-4027-A0CC-9D9F8ECA30CD",
  "edited": true,
  "exportOptions": {
    "_class": "exportOptions",
    "exportFormats": [
    ],
    "includedLayerIds": [
    ],
    "layerOptions": 0,
    "shouldTrim": false
  },
  "frame": {
    "_class": "rect",
    "constrainProportions": false,
    "height": 9.234678825193088,
    "width": 9.478231727715633,
    "x": 4.427961791988363,
    "y": 4.306446235189794
  },
  "hasClippingMask": false,
  "isClosed": true,
  "isFixedToViewport": false,
  "isFlippedHorizontal": false,
  "isFlippedVertical": false,
  "isLocked": false,
  "isVisible": true,
  "layerListExpandedType": 0,
  "maintainScrollPosition": false,
  "name": "🎨 Icon Colour",
  "nameIsFixed": false,
  "pointRadiusBehaviour": 1,
  "points": [
    {
      "_class": "curvePoint",
      "cornerRadius": 0,
      "curveFrom": "{0.58083879633098212, 0.95853860942759983}",
      "curveMode": 4,
      "curveTo": "{0.65022467285119945, 0.87889250772523431}",
      "hasCurveFrom": true,
      "hasCurveTo": false,
      "point": "{0.65022467285119945, 0.87889250772523431}"
    },
    {
      "_class": "curvePoint",
      "cornerRadius": 0,
      "curveFrom": "{0.16161616161616152, 1}",
      "curveMode": 3,
      "curveTo": "{0.48043018585838237, 1}",
      "hasCurveFrom": true,
      "hasCurveTo": true,
      "point": "{0.38383838383838387, 1}"
    },
    {
      "_class": "curvePoint",
      "cornerRadius": 0,
      "curveFrom": "{0, 0.24189526184538648}",
      "curveMode": 3,
      "curveTo": "{0, 0.82543640897755599}",
      "hasCurveFrom": true,
      "hasCurveTo": true,
      "point": "{0, 0.57107231920199519}"
    },
    {
      "_class": "curvePoint",
      "cornerRadius": 0,
      "curveFrom": "{0.60101010101010055, 0}",
      "curveMode": 3,
      "curveTo": "{0.22979797979797956, 0}",
      "hasCurveFrom": true,
      "hasCurveTo": true,
      "point": "{0.49999999999999972, 0}"
    },
    {
      "_class": "curvePoint",
      "cornerRadius": 0,
      "curveFrom": "{0.75505050505050453, 0.15211970074812955}",
      "curveMode": 4,
      "curveTo": "{0.71717171717171724, 0.047381546134663263}",
      "hasCurveFrom": false,
      "hasCurveTo": true,
      "point": "{0.75505050505050453, 0.15211970074812955}"
    },
    {
      "_class": "curvePoint",
      "cornerRadius": 0,
      "curveFrom": "{0.77777777777777746, 0.032418952618453775}",
      "curveMode": 1,
      "curveTo": "{0.77777777777777746, 0.032418952618453775}",
      "hasCurveFrom": false,
      "hasCurveTo": false,
      "point": "{0.77777777777777746, 0.032418952618453775}"
    },
    {
      "_class": "curvePoint",
      "cornerRadius": 0,
      "curveFrom": "{1, 0.032418952618453775}",
      "curveMode": 1,
      "curveTo": "{1, 0.032418952618453775}",
      "hasCurveFrom": false,
      "hasCurveTo": false,
      "point": "{1, 0.032418952618453775}"
    },
    {
      "_class": "curvePoint",
      "cornerRadius": 0,
      "curveFrom": "{0.7751142124640602, 0.68015878768650151}",
      "curveMode": 4,
      "curveTo": "{0.87308832388753843, 0.6188651902156207}",
      "hasCurveFrom": true,
      "hasCurveTo": false,
      "point": "{0.87308832388753843, 0.6188651902156207}"
    },
    {
      "_class": "curvePoint",
      "cornerRadius": 0,
      "curveFrom": "{0.65022467285232355, 0.87889250772301508}",
      "curveMode": 4,
      "curveTo": "{0.69685572608312862, 0.77087082644829996}",
      "hasCurveFrom": false,
      "hasCurveTo": true,
      "point": "{0.65022467285232355, 0.87889250772301508}"
    }
  ],
  "resizingConstraint": 63,
  "resizingType": 0,
  "rotation": 0,
  "shouldBreakMaskChain": false,
  "style": {
    "_class": "style",
    "blur": {
      "_class": "blur",
      "center": "{0.5, 0.5}",
      "isEnabled": false,
      "motionAngle": 0,
      "radius": 9.573971442137,
      "saturation": 1,
      "type": 0
    },
    "borderOptions": {
      "_class": "borderOptions",
      "dashPattern": [
      ],
      "isEnabled": true,
      "lineCapStyle": 0,
      "lineJoinStyle": 0
    },
    "borders": [
    ],
    "colorControls": {
      "_class": "colorControls",
      "brightness": 0,
      "contrast": 1,
      "hue": 0,
      "isEnabled": true,
      "saturation": 1
    },
    "contextSettings": {
      "_class": "graphicsContextSettings",
      "blendMode": 0,
      "opacity": 1
    },
    "do_objectID": "09AA99E7-6075-4B79-801B-D3E521E231D2",
    "endMarkerType": 0,
    "fills": [
      {
        "_class": "fill",
        "color": {
          "_class": "color",
          "alpha": 1,
          "blue": 0,
          "green": 0,
          "red": 0
        },
        "contextSettings": {
          "_class": "graphicsContextSettings",
          "blendMode": 0,
          "opacity": 1
        },
        "fillType": 0,
        "gradient": {
          "_class": "gradient",
          "elipseLength": 0,
          "from": "{0.5, 0}",
          "gradientType": 0,
          "stops": [
            {
              "_class": "gradientStop",
              "color": {
                "_class": "color",
                "alpha": 1,
                "blue": 1,
                "green": 1,
                "red": 1
              },
              "position": 0
            },
            {
              "_class": "gradientStop",
              "color": {
                "_class": "color",
                "alpha": 1,
                "blue": 0,
                "green": 0,
                "red": 0
              },
              "position": 1
            }
          ],
          "to": "{0.5, 1}"
        },
        "isEnabled": true,
        "noiseIndex": 0,
        "noiseIntensity": 0,
        "patternFillType": 1,
        "patternTileScale": 1
      }
    ],
    "innerShadows": [
    ],
    "miterLimit": 10,
    "shadows": [
    ],
    "startMarkerType": 0,
    "windingRule": 1
  }
}